infrable/__init__.py
infrable/errors.py
infrable/files.py
infrable/host.py
infrable/infra.py
infrable/init.py
infrable/meta.py
infrable/paths.py
infrable/readfile.py
infrable/service.py
infrable/switch.py
infrable/template.py
infrable/utils.py
infrable/cli/__init__.py
infrable/cli/files.py
infrable/cli/main.py
infrable/cli/remote.py
infrable/cli/switch.py
infrable-0.1.46.dist-info/METADATA
infrable-0.1.46.dist-info/WHEEL
infrable-0.1.46.dist-info/entry_points.txt
infrable-0.1.46.dist-info/licenses/LICENSE
infrable-0.1.46.dist-info/RECORD
