Metadata-Version: 2.4
Name: infrable
Version: 0.1.46
Summary: Manage infrastructure as a Python dev
Project-URL: Homepage, https://github.com/stckme/infrable
Author-email: Arijit Basu <sayanarijit@gmail.com>
Maintainer-email: Arijit Basu <sayanarijit@gmail.com>
License:                                  Apache License
License-File: LICENSE
Keywords: declarative,infrastructure,management
Requires-Python: >=3.12
Requires-Dist: ipython
Requires-Dist: jinja2
Requires-Dist: python-box
Requires-Dist: pyyaml
Requires-Dist: sh
Requires-Dist: tenacity>=9.1.2
Requires-Dist: tqdm
Requires-Dist: typer
Provides-Extra: devel
Requires-Dist: black; extra == 'devel'
Requires-Dist: build; extra == 'devel'
Requires-Dist: flake8; extra == 'devel'
Requires-Dist: isort; extra == 'devel'
Requires-Dist: pytest; extra == 'devel'
Requires-Dist: pytest-cov; extra == 'devel'
Requires-Dist: tox; extra == 'devel'
Requires-Dist: twine; extra == 'devel'
